__init__.py
portfolio.py
bigbucks_portfolio-0.1.dist-info/LICENSE
bigbucks_portfolio-0.1.dist-info/METADATA
bigbucks_portfolio-0.1.dist-info/WHEEL
bigbucks_portfolio-0.1.dist-info/top_level.txt
bigbucks_portfolio-0.1.dist-info/RECORD
